<?xml version="1.0" encoding="ISO-8859-1"?>
<poema>
	<autor>Fernando Pessoa</autor>
	<título>Autopsicografia</título>
	<estrofe>
		<verso><sílaba>O</sílaba> <sílaba>Po</sílaba><sílaba>e</sílaba><sílaba>ta</sílaba> <sílaba>é</sílaba> <sílaba>um</sílaba> <sílaba>fin</sílaba><sílaba>gi</sílaba><sílaba>dor</sílaba></verso>
		<verso><sílaba>Fin</sílaba><sílaba>ge</sílaba> <sílaba>tão</sílaba> <sílaba>com</sílaba><sílaba>ple</sílaba><sílaba>ta</sílaba><sílaba>men</sílaba><sílaba>te</sílaba></verso>
		<verso><sílaba>Que</sílaba> <sílaba>che</sílaba><sílaba>ga</sílaba> <sílaba>a</sílaba> <sílaba>fin</sílaba><sílaba>gir</sílaba> <sílaba>que</sílaba> <sílaba>é</sílaba> <sílaba>dor</sílaba></verso>
		<verso><sílaba>A</sílaba> <sílaba>dor</sílaba> <sílaba>que</sílaba> <sílaba>de</sílaba><sílaba>ve</sílaba><sílaba>ras</sílaba> <sílaba>sen</sílaba><sílaba>te</sílaba></verso>
	</estrofe>
	<estrofe>
		<verso><sílaba>E</sílaba> <sílaba>os</sílaba> <sílaba>que</sílaba> <sílaba>le</sílaba><sílaba>êm</sílaba> <sílaba>o</sílaba> <sílaba>que</sílaba> <sílaba>es</sílaba><sílaba>cre</sílaba><sílaba>ve</sílaba>,</verso>
		<verso><sílaba>Na</sílaba> <sílaba>dor</sílaba> <sílaba>li</sílaba><sílaba>da</sílaba> <sílaba>sen</sílaba><sílaba>tem</sílaba> <sílaba>bem,</sílaba></verso>
		<verso><sílaba>Não</sílaba> <sílaba>as</sílaba> <sílaba>du</sílaba><sílaba>as</sílaba> <sílaba>que</sílaba> <sílaba>ele</sílaba> <sílaba>te</sílaba><sílaba>ve</sílaba>,</verso>
		<verso><sílaba>Mas</sílaba> <sílaba>só</sílaba> <sílaba>a</sílaba> <sílaba>que</sílaba> <sílaba>e</sílaba><sílaba>les</sílaba> <sílaba>não</sílaba> <sílaba>têm</sílaba>.</verso>
	</estrofe>
	<estrofe>
		<verso><sílaba>E</sílaba> <sílaba>a</sílaba><sílaba>ssim</sílaba> <sílaba>nas</sílaba> <sílaba>ca</sílaba><sílaba>lhas</sílaba> <sílaba>da</sílaba> <sílaba>ro</sílaba><sílaba>da</sílaba></verso>
		<verso><sílaba>Gi</sílaba><sílaba>ra</sílaba>, <sílaba>a</sílaba> <sílaba>en</sílaba><sílaba>tre</sílaba><sílaba>ter</sílaba> <sílaba>a</sílaba> <sílaba>ra</sílaba><sílaba>zão</sílaba>,</verso>
		<verso><sílaba>E</sílaba><sílaba>sse</sílaba> <sílaba>com</sílaba><sílaba>boi</sílaba><sílaba>o</sílaba> <sílaba>de</sílaba> <sílaba>cor</sílaba><sílaba>da</sílaba></verso>
		<verso><sílaba>Que</sílaba> <sílaba>se</sílaba> <sílaba>cha</sílaba><sílaba>ma</sílaba> <sílaba>o</sílaba> <sílaba>co</sílaba><sílaba>ra</sílaba><sílaba>ção</sílaba>.</verso>
	</estrofe>
</poema>

